lokryn_pipe_audit/__init__.py
lokryn_pipe_audit/connectors.py
lokryn_pipe_audit/contracts.py
lokryn_pipe_audit/drivers.py
lokryn_pipe_audit/engine.py
lokryn_pipe_audit/errors.py
lokryn_pipe_audit/logging.py
lokryn_pipe_audit/movement.py
lokryn_pipe_audit/profiles.py
lokryn_pipe_audit/validators.py
lokryn_pipe_audit-0.1.0.dist-info/METADATA
lokryn_pipe_audit-0.1.0.dist-info/WHEEL
lokryn_pipe_audit-0.1.0.dist-info/licenses/LICENSE
lokryn_pipe_audit-0.1.0.dist-info/RECORD
