Metadata-Version: 2.4
Name: lokryn-pipe-audit
Version: 0.1.0
Summary: Data validation library for audit pipelines using Polars
Project-URL: Homepage, https://github.com/lokryn/pipe-audit-core
Project-URL: Documentation, https://github.com/lokryn/pipe-audit-core#readme
Project-URL: Repository, https://github.com/lokryn/pipe-audit-core
Author-email: Lokryn LLC <support@lokryn.com>
License-Expression: AGPL-3.0-only
License-File: LICENSE
Keywords: audit,compliance,contracts,data-quality,data-validation,polars
Classifier: Development Status :: 3 - Alpha
Classifier: Intended Audience :: Developers
Classifier: License :: OSI Approved :: GNU Affero General Public License v3
Classifier: Programming Language :: Python :: 3
Classifier: Programming Language :: Python :: 3.11
Classifier: Programming Language :: Python :: 3.12
Classifier: Topic :: Software Development :: Libraries :: Python Modules
Classifier: Topic :: Software Development :: Quality Assurance
Requires-Python: >=3.11
Requires-Dist: boto3>=1.34.0
Requires-Dist: httpx>=0.27.0
Requires-Dist: polars>=1.0.0
Requires-Dist: pyjwt[crypto]>=2.8.0
Provides-Extra: dev
Requires-Dist: boto3-stubs[s3]>=1.34.0; extra == 'dev'
Requires-Dist: moto[s3]>=5.0.0; extra == 'dev'
Requires-Dist: mypy>=1.8.0; extra == 'dev'
Requires-Dist: pytest-asyncio>=0.23.0; extra == 'dev'
Requires-Dist: pytest>=8.0.0; extra == 'dev'
Requires-Dist: ruff>=0.3.0; extra == 'dev'
